{"statusCode":200,"headers":{"Access-Control-Allow-Origin":"*","Access-Control-Allow-Headers":"*","Access-Control-Allow-Methods":"GET, OPTIONS","Content-Type":"application/json"},"body":"{\"userId\":\"8418c498-1021-70d0-38c8-3f038ccbc024\",\"sub\":\"8418c498-1021-70d0-38c8-3f038ccbc024\",\"email\":\"hammond@sheldonmedia.com\",\"emailVerified\":true,\"name\":\"Jedi Mystique\",\"userStatus\":\"CONFIRMED\",\"enabled\":true,\"createdAt\":\"2024-12-06T04:36:02.926Z\",\"updatedAt\":\"2026-01-22T04:29:36.283Z\"}"}